createllm/__init__.py
createllm/createllm.py
createllm-0.1.9.dist-info/AUTHORS.rst
createllm-0.1.9.dist-info/LICENSE
createllm-0.1.9.dist-info/METADATA
createllm-0.1.9.dist-info/WHEEL
createllm-0.1.9.dist-info/top_level.txt
createllm-0.1.9.dist-info/RECORD
