Metadata-Version: 2.2
Name: createllm
Version: 0.1.9
Summary: A Python package that enables users to create and train their own Language Learning Models (LLMs) from scratch using custom datasets. This package provides a simplified approach to building, training, and deploying custom language models tailored to specific domains or use cases.
Author-email: Khushal Jethava <khushaljethwa14@gmail.com>
Maintainer-email: Khushal Jethava <khushaljethwa14@gmail.com>
License: MIT license
Project-URL: bugs, https://github.com/khushaljethava/createllm/issues
Project-URL: changelog, https://github.com/khushaljethava/createllm/blob/master/changelog.md
Project-URL: homepage, https://github.com/khushaljethava/createllm
License-File: LICENSE
License-File: AUTHORS.rst
Provides-Extra: dev
Requires-Dist: coverage; extra == "dev"
Requires-Dist: mypy; extra == "dev"
Requires-Dist: pytest; extra == "dev"
Requires-Dist: ruff; extra == "dev"
